gjqh_DataFetch/DataFetch.cp310-win_amd64.pyd
gjqh_DataFetch/DataFetch.cp311-win_amd64.pyd
gjqh_DataFetch/DataFetch.cp312-win_amd64.pyd
gjqh_DataFetch/DataFetch.cp39-win_amd64.pyd
gjqh_DataFetch/DataFetch.cpython-39-x86_64-linux-gnu.so
gjqh_DataFetch/__init__.py
gjqh_DataFetch/example.py
gjqh_datafetch-0.0.6.dist-info/licenses/LICENSE.txt
gjqh_datafetch-0.0.6.dist-info/METADATA
gjqh_datafetch-0.0.6.dist-info/WHEEL
gjqh_datafetch-0.0.6.dist-info/top_level.txt
gjqh_datafetch-0.0.6.dist-info/RECORD
