Metadata-Version: 2.4
Name: gjqh_DataFetch
Version: 0.0.6
Summary: A simple trading API for internal use compatible with IS and XT trading systems.
Author-email: HongYuan <yuanhong2@gtht.com>
License-Expression: MIT
Project-URL: Homepage, https://github.com/pypa/sampleproject
Project-URL: Issues, https://github.com/pypa/sampleproject/issues
Classifier: Programming Language :: Python :: 3
Classifier: Operating System :: OS Independent
Requires-Python: >=3.9
License-File: LICENSE.txt
Requires-Dist: requests
Requires-Dist: clickhouse-connect==0.7.8
Requires-Dist: pandas>=1.5.0
Requires-Dist: redis
Requires-Dist: PyMySQL
Dynamic: license-file
